<annotation>
	<folder>Blouse</folder>
	<filename>001697.jpg</filename>
	<path>/home/honghaier1688/workspaces/Images/Blouse/001697.jpg</path>
	<source>
		<database>Unknown</database>
	</source>
	<size>
		<width>200</width>
		<height>300</height>
		<depth>3</depth>
	</size>
	<segmented>0</segmented>
	<object>
		<name>blouse</name>
		<pose>Unspecified</pose>
		<truncated>1</truncated>
		<difficult>0</difficult>
		<bndbox>
			<xmin>22</xmin>
			<ymin>47</ymin>
			<xmax>200</xmax>
			<ymax>225</ymax>
		</bndbox>
	</object>
</annotation>
