<annotation>
	<folder>Blouse</folder>
	<filename>001711.jpg</filename>
	<path>/home/honghaier1688/workspaces/Images/Blouse/001711.jpg</path>
	<source>
		<database>Unknown</database>
	</source>
	<size>
		<width>500</width>
		<height>690</height>
		<depth>3</depth>
	</size>
	<segmented>0</segmented>
	<object>
		<name>blouse</name>
		<pose>Unspecified</pose>
		<truncated>0</truncated>
		<difficult>0</difficult>
		<bndbox>
			<xmin>161</xmin>
			<ymin>175</ymin>
			<xmax>357</xmax>
			<ymax>372</ymax>
		</bndbox>
	</object>
</annotation>
